{
  "KLAC": {
    "symbol": "KLAC",
    "side": "long",
    "qty": 9.0,
    "entry_price": 217.15,
    "initial_stop_price": 174.82,
    "current_stop_price": 174.82,
    "r_per_share": 42.33000000000001,
    "stage": "initial",
    "extreme_price": 217.15,
    "stop_order_id": "63cf7840-4e16-421e-98a2-24c67ddb6e3b",
    "opened_at": "",
    "updated_at": ""
  },
  "SBUX": {
    "symbol": "SBUX",
    "side": "long",
    "qty": 10.0,
    "entry_price": 104.745,
    "initial_stop_price": 98.90214154924665,
    "current_stop_price": 98.90214154924665,
    "r_per_share": 5.842858450753348,
    "stage": "initial",
    "extreme_price": 104.745,
    "stop_order_id": "1e0fcf20-e23f-4c49-934e-ebaeb3a45b96",
    "opened_at": "2026-07-21T13:37:35.804849+00:00",
    "updated_at": "2026-07-21T13:37:35.804849+00:00"
  },
  "AMAT": {
    "symbol": "AMAT",
    "side": "long",
    "qty": 3.0,
    "entry_price": 550.613333,
    "initial_stop_price": 461.12363371149553,
    "current_stop_price": 461.12363371149553,
    "r_per_share": 89.4896992885045,
    "stage": "initial",
    "extreme_price": 550.613333,
    "stop_order_id": "3e3b0b15-f5a1-45af-96fd-151ffc889c26",
    "opened_at": "2026-07-22T13:38:35.309010+00:00",
    "updated_at": "2026-07-22T13:38:35.309010+00:00"
  }
}